pyroot_zen/RooArgList.py
pyroot_zen/RooArgSet.py
pyroot_zen/RooCategory.py
pyroot_zen/RooWorkspace.py
pyroot_zen/TH1.py
pyroot_zen/TH2.py
pyroot_zen/TMatrixTRow.py
pyroot_zen/TMatrixTSym.py
pyroot_zen/TMultiGraph.py
pyroot_zen/TObject.py
pyroot_zen/__init__.py
pyroot_zen/patch_ROOT.py
pyroot_zen/patch_RooFit.py
pyroot_zen/utils.py
pyroot_zen/entrypoints/__init__.py
pyroot_zen/entrypoints/at_cpp_lookup.py
pyroot_zen/entrypoints/at_roostats_lookup.py
pyroot_zen/entrypoints/at_tobject_callable.py
pyroot_zen/entrypoints/at_tobject_setter.py
pyroot_zen-1.1.4.dist-info/LICENSE.txt
pyroot_zen-1.1.4.dist-info/METADATA
pyroot_zen-1.1.4.dist-info/RECORD
pyroot_zen-1.1.4.dist-info/WHEEL
pyroot_zen-1.1.4.dist-info/pbr.json
pyroot_zen-1.1.4.dist-info/top_level.txt
