Metadata-Version: 2.1
Name: pyroot-zen
Version: 1.1.4
Summary: A wrapper around `PyROOT` for better syntax simplification.
Home-page: https://gitlab.com/ckhurewa/pyroot-zen
Author: Chitsanu Khurewathanakul
Author-email: chitsanu.khurewathanakul@gmail.com
License: GNU GPLv3
Platform: unix
Classifier: Development Status :: 4 - Beta
Classifier: Environment :: Console
Classifier: Intended Audience :: Developers
Classifier: Intended Audience :: Information Technology
Classifier: Operating System :: OS Independent
Classifier: Programming Language :: Python :: 2.7
Classifier: Topic :: Utilities
Requires-Python: ~=2.7
Requires-Dist: m2r
Requires-Dist: mock
